{
    "abbreviations": false, 
    "bibentries": false, 
    "bibsection": false, 
    "citation_items": false, 
    "citations": false, 
    "csl": "<style \n      xmlns=\"http://purl.org/net/xbiblio/csl\"\n      class=\"note\"\n      version=\"1.0\">\n  <info>\n    <id />\n    <title />\n    <updated>2009-08-10T04:49:00+09:00</updated>\n  </info>\n  <citation \n         et-al-min=\"6\"\n         et-al-use-first=\"5\">\n    <layout delimiter=\"; \">\n      <names variable=\"author\">\n        <name delimiter=\", \" initialize-with=\".\">\n          <name-part name=\"family\" text-case=\"uppercase\" />\n        </name>\n      </names>\n    </layout>\n  </citation>\n</style>", 
    "input": [
        {
            "author": [
                {
                    "family": "Чайковский", 
                    "given": "Пётр Ильич", 
                    "static-ordering": false
                }, 
                {
                    "family": "Winkle", 
                    "given": "Rip", 
                    "non-dropping-particle": "van", 
                    "static-ordering": false
                }, 
                {
                    "family": "我妻", 
                    "given": "栄", 
                    "static-ordering": false
                }, 
                {
                    "family": "Thucydides", 
                    "given": "Carl", 
                    "static-ordering": false, 
                    "suffix": "III"
                }, 
                {
                    "family": "Tokugawa", 
                    "given": "Ieyasu", 
                    "static-ordering": true
                }, 
                {
                    "given": "Prince", 
                    "static-ordering": false
                }
            ], 
            "id": "item-1", 
            "issued": {
                "date-parts": [
                    [
                        "2000"
                    ]
                ]
            }, 
            "title": "Our Story", 
            "type": "book"
        }
    ], 
    "mode": "citation", 
    "result": "П.И. ЧАЙКОВСКИЙ, R. VAN WINKLE, 我妻栄, C. THUCYDIDES III, TOKUGAWA I., et al."
}